pandocattributes.py
setup.py
pandoc_attributes.egg-info/PKG-INFO
pandoc_attributes.egg-info/SOURCES.txt
pandoc_attributes.egg-info/dependency_links.txt
pandoc_attributes.egg-info/requires.txt
pandoc_attributes.egg-info/top_level.txt