Metadata-Version: 1.0
Name: pandoc-attributes
Version: 0.1.6
Summary: An Attribute class to be used with pandocfilters
Home-page: http://github.com/aaren/pandoc-attributes
Author: Aaron O'Leary
Author-email: dev@aaren.me
License: BSD 2-Clause
Platform: UNKNOWN
